compare_form_response_tables.py
flipbook/__init__.py
flipbook/__main__.py
flipbook/data_page.py
flipbook/main_list.py
flipbook/save.py
flipbook/utils.py
flipbook/static/css/datatables.min.css
flipbook/static/css/semantic.min.css
flipbook/static/css/themes/default/assets/fonts/icons.ttf
flipbook/static/css/themes/default/assets/fonts/icons.woff
flipbook/static/css/themes/default/assets/fonts/icons.woff2
flipbook/static/images/favicon.png
flipbook/static/js/datatables.min.js
flipbook/static/js/jquery.min.js
flipbook/static/js/jquery.serialize-object.min.js
flipbook/static/js/pdfmake.min.js
flipbook/static/js/purl.min.js
flipbook/static/js/semantic.min.js
flipbook/static/js/vfs_fonts.js
flipbook/templates/data_page.html
flipbook/templates/main_list.html
flipbook-1.2.2.dist-info/LICENSE
flipbook-1.2.2.dist-info/METADATA
flipbook-1.2.2.dist-info/WHEEL
flipbook-1.2.2.dist-info/entry_points.txt
flipbook-1.2.2.dist-info/top_level.txt
flipbook-1.2.2.dist-info/RECORD
