Metadata-Version: 2.1
Name: flipbook
Version: 1.2.2
Summary: Starts a simple image server that lets you quickly flip through image files from a local directory using your web browser and optionally answering customizable questions about each one
Home-page: https://github.com/broadinstitute/flipbook
License: MIT
Keywords: curation,NGS,sequencing,STRs,REviewer,read visualization,machine learning
Classifier: Development Status :: 4 - Beta
Classifier: Intended Audience :: Developers
Classifier: License :: OSI Approved :: MIT License
Classifier: Natural Language :: English
Classifier: Programming Language :: Python :: 3
Classifier: Programming Language :: Python :: 3.7
Classifier: Programming Language :: Python :: 3.8
Classifier: Programming Language :: Python :: 3.9
Classifier: Programming Language :: Python :: Implementation :: CPython
Classifier: Programming Language :: Python :: Implementation :: PyPy
Requires-Python: >=3.7
License-File: LICENSE
Requires-Dist: configargparse >=1.5.5
Requires-Dist: flask-cors >=4.0.0
Requires-Dist: gunicorn >=21.2.0
Requires-Dist: jinja2 >=3.1.2
Requires-Dist: openpyxl >=3.1.1
Requires-Dist: pandas >=2.0.3
Requires-Dist: requests >=2.31.0
Requires-Dist: wcmatch >=8.4.1
Requires-Dist: xlrd >=2.0.1
Requires-Dist: xlwt >=1.3.0
Requires-Dist: flask ==2.1
Requires-Dist: Werkzeug ==2.0.0
